{
    "response": {
        "nombre": "OXIGENO DISUELTO",
        "tiposenal": "OX",
        "unidad": "ppm",
        "valores": [
            {
                "tag": "C310AI__14",
                "tiempo": "30/10/2025 18:00",
                "valor": 7.53,
                "value_formateado": "7.530",
                "remota": "C310",
                "tipo_consolidacion": "Un registro por hora"
            },
            {
                "tag": "C310AI__14",
                "tiempo": "30/10/2025 19:00",
                "valor": 7.21,
                "value_formateado": "7.210",
                "remota": "C310",
                "tipo_consolidacion": "Un registro por hora"
            },
            {
                "tag": "C310AI__14",
                "tiempo": "30/10/2025 20:00",
                "valor": 7.18,
                "value_formateado": "7.180",
                "remota": "C310",
                "tipo_consolidacion": "Un registro por hora"
            },
            {
                "tag": "C310AI__14",
                "tiempo": "30/10/2025 21:00",
                "valor": 7.21,
                "value_formateado": "7.210",
                "remota": "C310",
                "tipo_consolidacion": "Un registro por hora"
            },
            {
                "tag": "C310AI__14",
                "tiempo": "30/10/2025 22:00",
                "valor": 6.9,
                "value_formateado": "6.900",
                "remota": "C310",
                "tipo_consolidacion": "Un registro por hora"
            },
            {
                "tag": "C310AI__14",
                "tiempo": "30/10/2025 23:00",
                "valor": 6.81,
                "value_formateado": "6.810",
                "remota": "C310",
                "tipo_consolidacion": "Un registro por hora"
            },
            {
                "tag": "C310AI__14",
                "tiempo": "31/10/2025 00:00",
                "valor": 6.77,
                "value_formateado": "6.770",
                "remota": "C310",
                "tipo_consolidacion": "Un registro por hora"
            },
            {
                "tag": "C310AI__14",
                "tiempo": "31/10/2025 01:00",
                "valor": 6.67,
                "value_formateado": "6.670",
                "remota": "C310",
                "tipo_consolidacion": "Un registro por hora"
            },
            {
                "tag": "C310AI__14",
                "tiempo": "31/10/2025 02:00",
                "valor": 6.72,
                "value_formateado": "6.720",
                "remota": "C310",
                "tipo_consolidacion": "Un registro por hora"
            },
            {
                "tag": "C310AI__14",
                "tiempo": "31/10/2025 03:00",
                "valor": 6.46,
                "value_formateado": "6.460",
                "remota": "C310",
                "tipo_consolidacion": "Un registro por hora"
            },
            {
                "tag": "C310AI__14",
                "tiempo": "31/10/2025 04:00",
                "valor": 6.35,
                "value_formateado": "6.350",
                "remota": "C310",
                "tipo_consolidacion": "Un registro por hora"
            },
            {
                "tag": "C310AI__14",
                "tiempo": "31/10/2025 05:00",
                "valor": 6.64,
                "value_formateado": "6.640",
                "remota": "C310",
                "tipo_consolidacion": "Un registro por hora"
            },
            {
                "tag": "C310AI__14",
                "tiempo": "31/10/2025 06:00",
                "valor": 6.6,
                "value_formateado": "6.600",
                "remota": "C310",
                "tipo_consolidacion": "Un registro por hora"
            },
            {
                "tag": "C310AI__14",
                "tiempo": "31/10/2025 07:00",
                "valor": 6.7,
                "value_formateado": "6.700",
                "remota": "C310",
                "tipo_consolidacion": "Un registro por hora"
            },
            {
                "tag": "C310AI__14",
                "tiempo": "31/10/2025 08:00",
                "valor": 6.94,
                "value_formateado": "6.940",
                "remota": "C310",
                "tipo_consolidacion": "Un registro por hora"
            },
            {
                "tag": "C310AI__14",
                "tiempo": "31/10/2025 09:00",
                "valor": 6.95,
                "value_formateado": "6.950",
                "remota": "C310",
                "tipo_consolidacion": "Un registro por hora"
            },
            {
                "tag": "C310AI__14",
                "tiempo": "31/10/2025 10:00",
                "valor": 7.05,
                "value_formateado": "7.050",
                "remota": "C310",
                "tipo_consolidacion": "Un registro por hora"
            },
            {
                "tag": "C310AI__14",
                "tiempo": "31/10/2025 11:00",
                "valor": 7.26,
                "value_formateado": "7.260",
                "remota": "C310",
                "tipo_consolidacion": "Un registro por hora"
            },
            {
                "tag": "C310AI__14",
                "tiempo": "31/10/2025 12:00",
                "valor": 7.48,
                "value_formateado": "7.480",
                "remota": "C310",
                "tipo_consolidacion": "Un registro por hora"
            },
            {
                "tag": "C310AI__14",
                "tiempo": "31/10/2025 13:00",
                "valor": 7.69,
                "value_formateado": "7.690",
                "remota": "C310",
                "tipo_consolidacion": "Un registro por hora"
            },
            {
                "tag": "C310AI__14",
                "tiempo": "31/10/2025 14:00",
                "valor": 7.95,
                "value_formateado": "7.950",
                "remota": "C310",
                "tipo_consolidacion": "Un registro por hora"
            },
            {
                "tag": "C310AI__14",
                "tiempo": "31/10/2025 15:00",
                "valor": 7.95,
                "value_formateado": "7.950",
                "remota": "C310",
                "tipo_consolidacion": "Un registro por hora"
            },
            {
                "tag": "C310AI__14",
                "tiempo": "31/10/2025 16:00",
                "valor": 8.09,
                "value_formateado": "8.090",
                "remota": "C310",
                "tipo_consolidacion": "Un registro por hora"
            },
            {
                "tag": "C310AI__14",
                "tiempo": "31/10/2025 17:00",
                "valor": 8.05,
                "value_formateado": "8.050",
                "remota": "C310",
                "tipo_consolidacion": "Un registro por hora"
            },
            {
                "tag": "C310AI__14",
                "tiempo": "31/10/2025 18:00",
                "valor": 8.08,
                "value_formateado": "8.080",
                "remota": "C310",
                "tipo_consolidacion": "Un registro por hora"
            },
            {
                "tag": "C310AI__14",
                "tiempo": "31/10/2025 19:00",
                "valor": 7.98,
                "value_formateado": "7.980",
                "remota": "C310",
                "tipo_consolidacion": "Un registro por hora"
            },
            {
                "tag": "C310AI__14",
                "tiempo": "31/10/2025 20:00",
                "valor": 7.92,
                "value_formateado": "7.920",
                "remota": "C310",
                "tipo_consolidacion": "Un registro por hora"
            },
            {
                "tag": "C310AI__14",
                "tiempo": "31/10/2025 21:00",
                "valor": 7.71,
                "value_formateado": "7.710",
                "remota": "C310",
                "tipo_consolidacion": "Un registro por hora"
            },
            {
                "tag": "C310AI__14",
                "tiempo": "31/10/2025 22:00",
                "valor": 7.64,
                "value_formateado": "7.640",
                "remota": "C310",
                "tipo_consolidacion": "Un registro por hora"
            },
            {
                "tag": "C310AI__14",
                "tiempo": "31/10/2025 23:00",
                "valor": 7.47,
                "value_formateado": "7.470",
                "remota": "C310",
                "tipo_consolidacion": "Un registro por hora"
            },
            {
                "tag": "C310AI__14",
                "tiempo": "01/11/2025 00:00",
                "valor": 7.38,
                "value_formateado": "7.380",
                "remota": "C310",
                "tipo_consolidacion": "Un registro por hora"
            },
            {
                "tag": "C310AI__14",
                "tiempo": "01/11/2025 01:00",
                "valor": 7.2,
                "value_formateado": "7.200",
                "remota": "C310",
                "tipo_consolidacion": "Un registro por hora"
            },
            {
                "tag": "C310AI__14",
                "tiempo": "01/11/2025 02:00",
                "valor": 7.12,
                "value_formateado": "7.120",
                "remota": "C310",
                "tipo_consolidacion": "Un registro por hora"
            },
            {
                "tag": "C310AI__14",
                "tiempo": "01/11/2025 03:00",
                "valor": 7.01,
                "value_formateado": "7.010",
                "remota": "C310",
                "tipo_consolidacion": "Un registro por hora"
            },
            {
                "tag": "C310AI__14",
                "tiempo": "01/11/2025 04:00",
                "valor": 7.1,
                "value_formateado": "7.100",
                "remota": "C310",
                "tipo_consolidacion": "Un registro por hora"
            },
            {
                "tag": "C310AI__14",
                "tiempo": "01/11/2025 05:00",
                "valor": 7.07,
                "value_formateado": "7.070",
                "remota": "C310",
                "tipo_consolidacion": "Un registro por hora"
            },
            {
                "tag": "C310AI__14",
                "tiempo": "01/11/2025 06:00",
                "valor": 7.08,
                "value_formateado": "7.080",
                "remota": "C310",
                "tipo_consolidacion": "Un registro por hora"
            },
            {
                "tag": "C310AI__14",
                "tiempo": "01/11/2025 07:00",
                "valor": 6.9,
                "value_formateado": "6.900",
                "remota": "C310",
                "tipo_consolidacion": "Un registro por hora"
            },
            {
                "tag": "C310AI__14",
                "tiempo": "01/11/2025 08:00",
                "valor": 6.94,
                "value_formateado": "6.940",
                "remota": "C310",
                "tipo_consolidacion": "Un registro por hora"
            },
            {
                "tag": "C310AI__14",
                "tiempo": "01/11/2025 09:00",
                "valor": 6.68,
                "value_formateado": "6.680",
                "remota": "C310",
                "tipo_consolidacion": "Un registro por hora"
            },
            {
                "tag": "C310AI__14",
                "tiempo": "01/11/2025 10:00",
                "valor": 6.77,
                "value_formateado": "6.770",
                "remota": "C310",
                "tipo_consolidacion": "Un registro por hora"
            },
            {
                "tag": "C310AI__14",
                "tiempo": "01/11/2025 11:00",
                "valor": 6.86,
                "value_formateado": "6.860",
                "remota": "C310",
                "tipo_consolidacion": "Un registro por hora"
            },
            {
                "tag": "C310AI__14",
                "tiempo": "01/11/2025 12:00",
                "valor": 7.37,
                "value_formateado": "7.370",
                "remota": "C310",
                "tipo_consolidacion": "Un registro por hora"
            },
            {
                "tag": "C310AI__14",
                "tiempo": "01/11/2025 13:00",
                "valor": 7.17,
                "value_formateado": "7.170",
                "remota": "C310",
                "tipo_consolidacion": "Un registro por hora"
            },
            {
                "tag": "C310AI__14",
                "tiempo": "01/11/2025 14:00",
                "valor": 6.97,
                "value_formateado": "6.970",
                "remota": "C310",
                "tipo_consolidacion": "Un registro por hora"
            },
            {
                "tag": "C310AI__14",
                "tiempo": "01/11/2025 15:00",
                "valor": 7.67,
                "value_formateado": "7.670",
                "remota": "C310",
                "tipo_consolidacion": "Un registro por hora"
            },
            {
                "tag": "C310AI__14",
                "tiempo": "01/11/2025 16:00",
                "valor": 7.21,
                "value_formateado": "7.210",
                "remota": "C310",
                "tipo_consolidacion": "Un registro por hora"
            },
            {
                "tag": "C310AI__14",
                "tiempo": "01/11/2025 17:00",
                "valor": 7.35,
                "value_formateado": "7.350",
                "remota": "C310",
                "tipo_consolidacion": "Un registro por hora"
            },
            {
                "tag": "C310AI__14",
                "tiempo": "01/11/2025 18:00",
                "valor": 7.26,
                "value_formateado": "7.260",
                "remota": "C310",
                "tipo_consolidacion": "Un registro por hora"
            },
            {
                "tag": "C310AI__14",
                "tiempo": "01/11/2025 19:00",
                "valor": 6.93,
                "value_formateado": "6.930",
                "remota": "C310",
                "tipo_consolidacion": "Un registro por hora"
            },
            {
                "tag": "C310AI__14",
                "tiempo": "01/11/2025 20:00",
                "valor": 7,
                "value_formateado": "7.000",
                "remota": "C310",
                "tipo_consolidacion": "Un registro por hora"
            },
            {
                "tag": "C310AI__14",
                "tiempo": "01/11/2025 21:00",
                "valor": 6.98,
                "value_formateado": "6.980",
                "remota": "C310",
                "tipo_consolidacion": "Un registro por hora"
            },
            {
                "tag": "C310AI__14",
                "tiempo": "01/11/2025 22:00",
                "valor": 7.22,
                "value_formateado": "7.220",
                "remota": "C310",
                "tipo_consolidacion": "Un registro por hora"
            },
            {
                "tag": "C310AI__14",
                "tiempo": "01/11/2025 23:00",
                "valor": 6.75,
                "value_formateado": "6.750",
                "remota": "C310",
                "tipo_consolidacion": "Un registro por hora"
            },
            {
                "tag": "C310AI__14",
                "tiempo": "02/11/2025 00:00",
                "valor": 7.07,
                "value_formateado": "7.070",
                "remota": "C310",
                "tipo_consolidacion": "Un registro por hora"
            },
            {
                "tag": "C310AI__14",
                "tiempo": "02/11/2025 01:00",
                "valor": 6.91,
                "value_formateado": "6.910",
                "remota": "C310",
                "tipo_consolidacion": "Un registro por hora"
            },
            {
                "tag": "C310AI__14",
                "tiempo": "02/11/2025 02:00",
                "valor": 6.49,
                "value_formateado": "6.490",
                "remota": "C310",
                "tipo_consolidacion": "Un registro por hora"
            },
            {
                "tag": "C310AI__14",
                "tiempo": "02/11/2025 03:00",
                "valor": 6.61,
                "value_formateado": "6.610",
                "remota": "C310",
                "tipo_consolidacion": "Un registro por hora"
            },
            {
                "tag": "C310AI__14",
                "tiempo": "02/11/2025 04:00",
                "valor": 6.51,
                "value_formateado": "6.510",
                "remota": "C310",
                "tipo_consolidacion": "Un registro por hora"
            },
            {
                "tag": "C310AI__14",
                "tiempo": "02/11/2025 05:00",
                "valor": 6.51,
                "value_formateado": "6.510",
                "remota": "C310",
                "tipo_consolidacion": "Un registro por hora"
            },
            {
                "tag": "C310AI__14",
                "tiempo": "02/11/2025 06:00",
                "valor": 6.56,
                "value_formateado": "6.560",
                "remota": "C310",
                "tipo_consolidacion": "Un registro por hora"
            },
            {
                "tag": "C310AI__14",
                "tiempo": "02/11/2025 07:00",
                "valor": 6.65,
                "value_formateado": "6.650",
                "remota": "C310",
                "tipo_consolidacion": "Un registro por hora"
            },
            {
                "tag": "C310AI__14",
                "tiempo": "02/11/2025 08:00",
                "valor": 6.5,
                "value_formateado": "6.500",
                "remota": "C310",
                "tipo_consolidacion": "Un registro por hora"
            },
            {
                "tag": "C310AI__14",
                "tiempo": "02/11/2025 09:00",
                "valor": 6.73,
                "value_formateado": "6.730",
                "remota": "C310",
                "tipo_consolidacion": "Un registro por hora"
            },
            {
                "tag": "C310AI__14",
                "tiempo": "02/11/2025 10:00",
                "valor": 6.63,
                "value_formateado": "6.630",
                "remota": "C310",
                "tipo_consolidacion": "Un registro por hora"
            },
            {
                "tag": "C310AI__14",
                "tiempo": "02/11/2025 11:00",
                "valor": 6.53,
                "value_formateado": "6.530",
                "remota": "C310",
                "tipo_consolidacion": "Un registro por hora"
            },
            {
                "tag": "C310AI__14",
                "tiempo": "02/11/2025 12:00",
                "valor": 6.7,
                "value_formateado": "6.700",
                "remota": "C310",
                "tipo_consolidacion": "Un registro por hora"
            },
            {
                "tag": "C310AI__14",
                "tiempo": "02/11/2025 13:00",
                "valor": 7.19,
                "value_formateado": "7.190",
                "remota": "C310",
                "tipo_consolidacion": "Un registro por hora"
            },
            {
                "tag": "C310AI__14",
                "tiempo": "02/11/2025 14:00",
                "valor": 7.05,
                "value_formateado": "7.050",
                "remota": "C310",
                "tipo_consolidacion": "Un registro por hora"
            },
            {
                "tag": "C310AI__14",
                "tiempo": "02/11/2025 15:00",
                "valor": 7.38,
                "value_formateado": "7.380",
                "remota": "C310",
                "tipo_consolidacion": "Un registro por hora"
            },
            {
                "tag": "C310AI__14",
                "tiempo": "02/11/2025 16:00",
                "valor": 7.5,
                "value_formateado": "7.500",
                "remota": "C310",
                "tipo_consolidacion": "Un registro por hora"
            },
            {
                "tag": "C310AI__14",
                "tiempo": "02/11/2025 17:00",
                "valor": 7.4,
                "value_formateado": "7.400",
                "remota": "C310",
                "tipo_consolidacion": "Un registro por hora"
            },
            {
                "tag": "C310AI__14",
                "tiempo": "02/11/2025 18:00",
                "valor": 7.57,
                "value_formateado": "7.570",
                "remota": "C310",
                "tipo_consolidacion": "Un registro por hora"
            },
            {
                "tag": "C310AI__14",
                "tiempo": "02/11/2025 19:00",
                "valor": 7.45,
                "value_formateado": "7.450",
                "remota": "C310",
                "tipo_consolidacion": "Un registro por hora"
            },
            {
                "tag": "C310AI__14",
                "tiempo": "02/11/2025 20:00",
                "valor": 7.38,
                "value_formateado": "7.380",
                "remota": "C310",
                "tipo_consolidacion": "Un registro por hora"
            },
            {
                "tag": "C310AI__14",
                "tiempo": "02/11/2025 21:00",
                "valor": 6.92,
                "value_formateado": "6.920",
                "remota": "C310",
                "tipo_consolidacion": "Un registro por hora"
            },
            {
                "tag": "C310AI__14",
                "tiempo": "02/11/2025 22:00",
                "valor": 6.91,
                "value_formateado": "6.910",
                "remota": "C310",
                "tipo_consolidacion": "Un registro por hora"
            },
            {
                "tag": "C310AI__14",
                "tiempo": "02/11/2025 23:00",
                "valor": 6.79,
                "value_formateado": "6.790",
                "remota": "C310",
                "tipo_consolidacion": "Un registro por hora"
            },
            {
                "tag": "C310AI__14",
                "tiempo": "03/11/2025 00:00",
                "valor": 6.54,
                "value_formateado": "6.540",
                "remota": "C310",
                "tipo_consolidacion": "Un registro por hora"
            },
            {
                "tag": "C310AI__14",
                "tiempo": "03/11/2025 01:00",
                "valor": 6.58,
                "value_formateado": "6.580",
                "remota": "C310",
                "tipo_consolidacion": "Un registro por hora"
            },
            {
                "tag": "C310AI__14",
                "tiempo": "03/11/2025 02:00",
                "valor": 6.43,
                "value_formateado": "6.430",
                "remota": "C310",
                "tipo_consolidacion": "Un registro por hora"
            },
            {
                "tag": "C310AI__14",
                "tiempo": "03/11/2025 03:00",
                "valor": 6.18,
                "value_formateado": "6.180",
                "remota": "C310",
                "tipo_consolidacion": "Un registro por hora"
            },
            {
                "tag": "C310AI__14",
                "tiempo": "03/11/2025 04:00",
                "valor": 6.27,
                "value_formateado": "6.270",
                "remota": "C310",
                "tipo_consolidacion": "Un registro por hora"
            },
            {
                "tag": "C310AI__14",
                "tiempo": "03/11/2025 05:00",
                "valor": 6.01,
                "value_formateado": "6.010",
                "remota": "C310",
                "tipo_consolidacion": "Un registro por hora"
            },
            {
                "tag": "C310AI__14",
                "tiempo": "03/11/2025 06:00",
                "valor": 6.24,
                "value_formateado": "6.240",
                "remota": "C310",
                "tipo_consolidacion": "Un registro por hora"
            },
            {
                "tag": "C310AI__14",
                "tiempo": "03/11/2025 07:00",
                "valor": 6.07,
                "value_formateado": "6.070",
                "remota": "C310",
                "tipo_consolidacion": "Un registro por hora"
            },
            {
                "tag": "C310AI__14",
                "tiempo": "03/11/2025 08:00",
                "valor": 6.04,
                "value_formateado": "6.040",
                "remota": "C310",
                "tipo_consolidacion": "Un registro por hora"
            },
            {
                "tag": "C310AI__14",
                "tiempo": "03/11/2025 09:00",
                "valor": 5.84,
                "value_formateado": "5.840",
                "remota": "C310",
                "tipo_consolidacion": "Un registro por hora"
            },
            {
                "tag": "C310AI__14",
                "tiempo": "03/11/2025 10:00",
                "valor": 5.98,
                "value_formateado": "5.980",
                "remota": "C310",
                "tipo_consolidacion": "Un registro por hora"
            },
            {
                "tag": "C310AI__14",
                "tiempo": "03/11/2025 11:00",
                "valor": 6.19,
                "value_formateado": "6.190",
                "remota": "C310",
                "tipo_consolidacion": "Un registro por hora"
            },
            {
                "tag": "C310AI__14",
                "tiempo": "03/11/2025 12:00",
                "valor": 6.44,
                "value_formateado": "6.440",
                "remota": "C310",
                "tipo_consolidacion": "Un registro por hora"
            },
            {
                "tag": "C310AI__14",
                "tiempo": "03/11/2025 13:00",
                "valor": 6.53,
                "value_formateado": "6.530",
                "remota": "C310",
                "tipo_consolidacion": "Un registro por hora"
            },
            {
                "tag": "C310AI__14",
                "tiempo": "03/11/2025 14:00",
                "valor": 7.11,
                "value_formateado": "7.110",
                "remota": "C310",
                "tipo_consolidacion": "Un registro por hora"
            },
            {
                "tag": "C310AI__14",
                "tiempo": "03/11/2025 15:00",
                "valor": 6.95,
                "value_formateado": "6.950",
                "remota": "C310",
                "tipo_consolidacion": "Un registro por hora"
            },
            {
                "tag": "C310AI__14",
                "tiempo": "03/11/2025 16:00",
                "valor": 6.91,
                "value_formateado": "6.910",
                "remota": "C310",
                "tipo_consolidacion": "Un registro por hora"
            },
            {
                "tag": "C310AI__14",
                "tiempo": "03/11/2025 17:00",
                "valor": 7.56,
                "value_formateado": "7.560",
                "remota": "C310",
                "tipo_consolidacion": "Un registro por hora"
            },
            {
                "tag": "C310AI__14",
                "tiempo": "03/11/2025 18:00",
                "valor": 7.08,
                "value_formateado": "7.080",
                "remota": "C310",
                "tipo_consolidacion": "Un registro por hora"
            },
            {
                "tag": "C310AI__14",
                "tiempo": "03/11/2025 19:00",
                "valor": 7.44,
                "value_formateado": "7.440",
                "remota": "C310",
                "tipo_consolidacion": "Un registro por hora"
            },
            {
                "tag": "C310AI__14",
                "tiempo": "03/11/2025 20:00",
                "valor": 6.96,
                "value_formateado": "6.960",
                "remota": "C310",
                "tipo_consolidacion": "Un registro por hora"
            },
            {
                "tag": "C310AI__14",
                "tiempo": "03/11/2025 21:00",
                "valor": 7.02,
                "value_formateado": "7.020",
                "remota": "C310",
                "tipo_consolidacion": "Un registro por hora"
            },
            {
                "tag": "C310AI__14",
                "tiempo": "03/11/2025 22:00",
                "valor": 7.29,
                "value_formateado": "7.290",
                "remota": "C310",
                "tipo_consolidacion": "Un registro por hora"
            },
            {
                "tag": "C310AI__14",
                "tiempo": "03/11/2025 23:00",
                "valor": 6.89,
                "value_formateado": "6.890",
                "remota": "C310",
                "tipo_consolidacion": "Un registro por hora"
            },
            {
                "tag": "C310AI__14",
                "tiempo": "04/11/2025 00:00",
                "valor": 6.69,
                "value_formateado": "6.690",
                "remota": "C310",
                "tipo_consolidacion": "Un registro por hora"
            },
            {
                "tag": "C310AI__14",
                "tiempo": "04/11/2025 01:00",
                "valor": 6.78,
                "value_formateado": "6.780",
                "remota": "C310",
                "tipo_consolidacion": "Un registro por hora"
            },
            {
                "tag": "C310AI__14",
                "tiempo": "04/11/2025 02:00",
                "valor": 6.65,
                "value_formateado": "6.650",
                "remota": "C310",
                "tipo_consolidacion": "Un registro por hora"
            },
            {
                "tag": "C310AI__14",
                "tiempo": "04/11/2025 03:00",
                "valor": 6.68,
                "value_formateado": "6.680",
                "remota": "C310",
                "tipo_consolidacion": "Un registro por hora"
            },
            {
                "tag": "C310AI__14",
                "tiempo": "04/11/2025 04:00",
                "valor": 6.67,
                "value_formateado": "6.670",
                "remota": "C310",
                "tipo_consolidacion": "Un registro por hora"
            },
            {
                "tag": "C310AI__14",
                "tiempo": "04/11/2025 05:00",
                "valor": 6.33,
                "value_formateado": "6.330",
                "remota": "C310",
                "tipo_consolidacion": "Un registro por hora"
            },
            {
                "tag": "C310AI__14",
                "tiempo": "04/11/2025 06:00",
                "valor": 6.29,
                "value_formateado": "6.290",
                "remota": "C310",
                "tipo_consolidacion": "Un registro por hora"
            },
            {
                "tag": "C310AI__14",
                "tiempo": "04/11/2025 07:00",
                "valor": 6.17,
                "value_formateado": "6.170",
                "remota": "C310",
                "tipo_consolidacion": "Un registro por hora"
            },
            {
                "tag": "C310AI__14",
                "tiempo": "04/11/2025 08:00",
                "valor": 6.24,
                "value_formateado": "6.240",
                "remota": "C310",
                "tipo_consolidacion": "Un registro por hora"
            },
            {
                "tag": "C310AI__14",
                "tiempo": "04/11/2025 09:00",
                "valor": 6.09,
                "value_formateado": "6.090",
                "remota": "C310",
                "tipo_consolidacion": "Un registro por hora"
            },
            {
                "tag": "C310AI__14",
                "tiempo": "04/11/2025 10:00",
                "valor": 6.22,
                "value_formateado": "6.220",
                "remota": "C310",
                "tipo_consolidacion": "Un registro por hora"
            },
            {
                "tag": "C310AI__14",
                "tiempo": "04/11/2025 11:00",
                "valor": 6.58,
                "value_formateado": "6.580",
                "remota": "C310",
                "tipo_consolidacion": "Un registro por hora"
            },
            {
                "tag": "C310AI__14",
                "tiempo": "04/11/2025 12:00",
                "valor": 6.83,
                "value_formateado": "6.830",
                "remota": "C310",
                "tipo_consolidacion": "Un registro por hora"
            },
            {
                "tag": "C310AI__14",
                "tiempo": "04/11/2025 13:00",
                "valor": 6.83,
                "value_formateado": "6.830",
                "remota": "C310",
                "tipo_consolidacion": "Un registro por hora"
            },
            {
                "tag": "C310AI__14",
                "tiempo": "04/11/2025 14:00",
                "valor": 7.21,
                "value_formateado": "7.210",
                "remota": "C310",
                "tipo_consolidacion": "Un registro por hora"
            },
            {
                "tag": "C310AI__14",
                "tiempo": "04/11/2025 15:00",
                "valor": 7.31,
                "value_formateado": "7.310",
                "remota": "C310",
                "tipo_consolidacion": "Un registro por hora"
            },
            {
                "tag": "C310AI__14",
                "tiempo": "04/11/2025 16:00",
                "valor": 7.26,
                "value_formateado": "7.260",
                "remota": "C310",
                "tipo_consolidacion": "Un registro por hora"
            },
            {
                "tag": "C310AI__14",
                "tiempo": "04/11/2025 17:00",
                "valor": 7.44,
                "value_formateado": "7.440",
                "remota": "C310",
                "tipo_consolidacion": "Un registro por hora"
            },
            {
                "tag": "C310AI__14",
                "tiempo": "04/11/2025 18:00",
                "valor": 7.25,
                "value_formateado": "7.250",
                "remota": "C310",
                "tipo_consolidacion": "Un registro por hora"
            },
            {
                "tag": "C310AI__14",
                "tiempo": "04/11/2025 19:00",
                "valor": 7.34,
                "value_formateado": "7.340",
                "remota": "C310",
                "tipo_consolidacion": "Un registro por hora"
            },
            {
                "tag": "C310AI__14",
                "tiempo": "04/11/2025 20:00",
                "valor": 7.28,
                "value_formateado": "7.280",
                "remota": "C310",
                "tipo_consolidacion": "Un registro por hora"
            },
            {
                "tag": "C310AI__14",
                "tiempo": "04/11/2025 21:00",
                "valor": 7.38,
                "value_formateado": "7.380",
                "remota": "C310",
                "tipo_consolidacion": "Un registro por hora"
            },
            {
                "tag": "C310AI__14",
                "tiempo": "04/11/2025 22:00",
                "valor": 7.16,
                "value_formateado": "7.160",
                "remota": "C310",
                "tipo_consolidacion": "Un registro por hora"
            },
            {
                "tag": "C310AI__14",
                "tiempo": "04/11/2025 23:00",
                "valor": 7.15,
                "value_formateado": "7.150",
                "remota": "C310",
                "tipo_consolidacion": "Un registro por hora"
            },
            {
                "tag": "C310AI__14",
                "tiempo": "05/11/2025 00:00",
                "valor": 7.15,
                "value_formateado": "7.150",
                "remota": "C310",
                "tipo_consolidacion": "Un registro por hora"
            },
            {
                "tag": "C310AI__14",
                "tiempo": "05/11/2025 01:00",
                "valor": 7.06,
                "value_formateado": "7.060",
                "remota": "C310",
                "tipo_consolidacion": "Un registro por hora"
            },
            {
                "tag": "C310AI__14",
                "tiempo": "05/11/2025 02:00",
                "valor": 6.85,
                "value_formateado": "6.850",
                "remota": "C310",
                "tipo_consolidacion": "Un registro por hora"
            },
            {
                "tag": "C310AI__14",
                "tiempo": "05/11/2025 03:00",
                "valor": 6.57,
                "value_formateado": "6.570",
                "remota": "C310",
                "tipo_consolidacion": "Un registro por hora"
            },
            {
                "tag": "C310AI__14",
                "tiempo": "05/11/2025 04:00",
                "valor": 6.42,
                "value_formateado": "6.420",
                "remota": "C310",
                "tipo_consolidacion": "Un registro por hora"
            },
            {
                "tag": "C310AI__14",
                "tiempo": "05/11/2025 05:00",
                "valor": 6.6,
                "value_formateado": "6.600",
                "remota": "C310",
                "tipo_consolidacion": "Un registro por hora"
            },
            {
                "tag": "C310AI__14",
                "tiempo": "05/11/2025 06:00",
                "valor": 6.31,
                "value_formateado": "6.310",
                "remota": "C310",
                "tipo_consolidacion": "Un registro por hora"
            },
            {
                "tag": "C310AI__14",
                "tiempo": "05/11/2025 07:00",
                "valor": 6.44,
                "value_formateado": "6.440",
                "remota": "C310",
                "tipo_consolidacion": "Un registro por hora"
            },
            {
                "tag": "C310AI__14",
                "tiempo": "05/11/2025 08:00",
                "valor": 6.18,
                "value_formateado": "6.180",
                "remota": "C310",
                "tipo_consolidacion": "Un registro por hora"
            },
            {
                "tag": "C310AI__14",
                "tiempo": "05/11/2025 09:00",
                "valor": 5.93,
                "value_formateado": "5.930",
                "remota": "C310",
                "tipo_consolidacion": "Un registro por hora"
            },
            {
                "tag": "C310AI__14",
                "tiempo": "05/11/2025 10:00",
                "valor": 5.88,
                "value_formateado": "5.880",
                "remota": "C310",
                "tipo_consolidacion": "Un registro por hora"
            },
            {
                "tag": "C310AI__14",
                "tiempo": "05/11/2025 11:00",
                "valor": 6.42,
                "value_formateado": "6.420",
                "remota": "C310",
                "tipo_consolidacion": "Un registro por hora"
            },
            {
                "tag": "C310AI__14",
                "tiempo": "05/11/2025 12:00",
                "valor": 6.6,
                "value_formateado": "6.600",
                "remota": "C310",
                "tipo_consolidacion": "Un registro por hora"
            },
            {
                "tag": "C310AI__14",
                "tiempo": "05/11/2025 13:00",
                "valor": 6.5,
                "value_formateado": "6.500",
                "remota": "C310",
                "tipo_consolidacion": "Un registro por hora"
            },
            {
                "tag": "C310AI__14",
                "tiempo": "05/11/2025 14:00",
                "valor": 6.72,
                "value_formateado": "6.720",
                "remota": "C310",
                "tipo_consolidacion": "Un registro por hora"
            },
            {
                "tag": "C310AI__14",
                "tiempo": "05/11/2025 15:00",
                "valor": 6.7,
                "value_formateado": "6.700",
                "remota": "C310",
                "tipo_consolidacion": "Un registro por hora"
            },
            {
                "tag": "C310AI__14",
                "tiempo": "05/11/2025 16:00",
                "valor": 6.71,
                "value_formateado": "6.710",
                "remota": "C310",
                "tipo_consolidacion": "Un registro por hora"
            },
            {
                "tag": "C310AI__14",
                "tiempo": "05/11/2025 17:00",
                "valor": 7.3,
                "value_formateado": "7.300",
                "remota": "C310",
                "tipo_consolidacion": "Un registro por hora"
            },
            {
                "tag": "C310AI__14",
                "tiempo": "05/11/2025 18:00",
                "valor": 6.62,
                "value_formateado": "6.620",
                "remota": "C310",
                "tipo_consolidacion": "Un registro por hora"
            },
            {
                "tag": "C310AI__14",
                "tiempo": "05/11/2025 19:00",
                "valor": 6.8,
                "value_formateado": "6.800",
                "remota": "C310",
                "tipo_consolidacion": "Un registro por hora"
            },
            {
                "tag": "C310AI__14",
                "tiempo": "05/11/2025 20:00",
                "valor": 6.69,
                "value_formateado": "6.690",
                "remota": "C310",
                "tipo_consolidacion": "Un registro por hora"
            },
            {
                "tag": "C310AI__14",
                "tiempo": "05/11/2025 21:00",
                "valor": 6.69,
                "value_formateado": "6.690",
                "remota": "C310",
                "tipo_consolidacion": "Un registro por hora"
            },
            {
                "tag": "C310AI__14",
                "tiempo": "05/11/2025 22:00",
                "valor": 6.8,
                "value_formateado": "6.800",
                "remota": "C310",
                "tipo_consolidacion": "Un registro por hora"
            },
            {
                "tag": "C310AI__14",
                "tiempo": "05/11/2025 23:00",
                "valor": 6.16,
                "value_formateado": "6.160",
                "remota": "C310",
                "tipo_consolidacion": "Un registro por hora"
            },
            {
                "tag": "C310AI__14",
                "tiempo": "06/11/2025 00:00",
                "valor": 6.2,
                "value_formateado": "6.200",
                "remota": "C310",
                "tipo_consolidacion": "Un registro por hora"
            },
            {
                "tag": "C310AI__14",
                "tiempo": "06/11/2025 01:00",
                "valor": 6.34,
                "value_formateado": "6.340",
                "remota": "C310",
                "tipo_consolidacion": "Un registro por hora"
            },
            {
                "tag": "C310AI__14",
                "tiempo": "06/11/2025 02:00",
                "valor": 6.4,
                "value_formateado": "6.400",
                "remota": "C310",
                "tipo_consolidacion": "Un registro por hora"
            },
            {
                "tag": "C310AI__14",
                "tiempo": "06/11/2025 03:00",
                "valor": 6.29,
                "value_formateado": "6.290",
                "remota": "C310",
                "tipo_consolidacion": "Un registro por hora"
            },
            {
                "tag": "C310AI__14",
                "tiempo": "06/11/2025 04:00",
                "valor": 5.9,
                "value_formateado": "5.900",
                "remota": "C310",
                "tipo_consolidacion": "Un registro por hora"
            },
            {
                "tag": "C310AI__14",
                "tiempo": "06/11/2025 05:00",
                "valor": 6.09,
                "value_formateado": "6.090",
                "remota": "C310",
                "tipo_consolidacion": "Un registro por hora"
            },
            {
                "tag": "C310AI__14",
                "tiempo": "06/11/2025 06:00",
                "valor": 5.85,
                "value_formateado": "5.850",
                "remota": "C310",
                "tipo_consolidacion": "Un registro por hora"
            },
            {
                "tag": "C310AI__14",
                "tiempo": "06/11/2025 07:00",
                "valor": 5.77,
                "value_formateado": "5.770",
                "remota": "C310",
                "tipo_consolidacion": "Un registro por hora"
            },
            {
                "tag": "C310AI__14",
                "tiempo": "06/11/2025 08:00",
                "valor": 5.7,
                "value_formateado": "5.700",
                "remota": "C310",
                "tipo_consolidacion": "Un registro por hora"
            },
            {
                "tag": "C310AI__14",
                "tiempo": "06/11/2025 09:00",
                "valor": 5.66,
                "value_formateado": "5.660",
                "remota": "C310",
                "tipo_consolidacion": "Un registro por hora"
            },
            {
                "tag": "C310AI__14",
                "tiempo": "06/11/2025 10:00",
                "valor": 5.57,
                "value_formateado": "5.570",
                "remota": "C310",
                "tipo_consolidacion": "Un registro por hora"
            },
            {
                "tag": "C310AI__14",
                "tiempo": "06/11/2025 11:00",
                "valor": 6.46,
                "value_formateado": "6.460",
                "remota": "C310",
                "tipo_consolidacion": "Un registro por hora"
            },
            {
                "tag": "C310AI__14",
                "tiempo": "06/11/2025 12:00",
                "valor": 6.81,
                "value_formateado": "6.810",
                "remota": "C310",
                "tipo_consolidacion": "Un registro por hora"
            },
            {
                "tag": "C310AI__14",
                "tiempo": "06/11/2025 13:00",
                "valor": 7.04,
                "value_formateado": "7.040",
                "remota": "C310",
                "tipo_consolidacion": "Un registro por hora"
            },
            {
                "tag": "C310AI__14",
                "tiempo": "06/11/2025 14:00",
                "valor": 7.28,
                "value_formateado": "7.280",
                "remota": "C310",
                "tipo_consolidacion": "Un registro por hora"
            },
            {
                "tag": "C310AI__14",
                "tiempo": "06/11/2025 15:00",
                "valor": 7.42,
                "value_formateado": "7.420",
                "remota": "C310",
                "tipo_consolidacion": "Un registro por hora"
            },
            {
                "tag": "C310AI__14",
                "tiempo": "06/11/2025 16:00",
                "valor": 7.56,
                "value_formateado": "7.560",
                "remota": "C310",
                "tipo_consolidacion": "Un registro por hora"
            },
            {
                "tag": "C310AI__14",
                "tiempo": "06/11/2025 17:00",
                "valor": 7.56,
                "value_formateado": "7.560",
                "remota": "C310",
                "tipo_consolidacion": "Un registro por hora"
            },
            {
                "tag": "C310AI__14",
                "tiempo": "06/11/2025 18:00",
                "valor": 7.5,
                "value_formateado": "7.500",
                "remota": "C310",
                "tipo_consolidacion": "Un registro por hora"
            },
            {
                "tag": "C310AI__14",
                "tiempo": "06/11/2025 19:00",
                "valor": 7.18,
                "value_formateado": "7.180",
                "remota": "C310",
                "tipo_consolidacion": "Un registro por hora"
            },
            {
                "tag": "C310AI__14",
                "tiempo": "06/11/2025 20:00",
                "valor": 7.15,
                "value_formateado": "7.150",
                "remota": "C310",
                "tipo_consolidacion": "Un registro por hora"
            },
            {
                "tag": "C310AI__14",
                "tiempo": "06/11/2025 21:00",
                "valor": 6.75,
                "value_formateado": "6.750",
                "remota": "C310",
                "tipo_consolidacion": "Un registro por hora"
            },
            {
                "tag": "C310AI__14",
                "tiempo": "06/11/2025 22:00",
                "valor": 6.59,
                "value_formateado": "6.590",
                "remota": "C310",
                "tipo_consolidacion": "Un registro por hora"
            },
            {
                "tag": "C310AI__14",
                "tiempo": "06/11/2025 23:00",
                "valor": 6.71,
                "value_formateado": "6.710",
                "remota": "C310",
                "tipo_consolidacion": "Un registro por hora"
            },
            {
                "tag": "C310AI__14",
                "tiempo": "07/11/2025 00:00",
                "valor": 6.7,
                "value_formateado": "6.700",
                "remota": "C310",
                "tipo_consolidacion": "Un registro por hora"
            },
            {
                "tag": "C310AI__14",
                "tiempo": "07/11/2025 01:00",
                "valor": 6.85,
                "value_formateado": "6.850",
                "remota": "C310",
                "tipo_consolidacion": "Un registro por hora"
            },
            {
                "tag": "C310AI__14",
                "tiempo": "07/11/2025 02:00",
                "valor": 6.7,
                "value_formateado": "6.700",
                "remota": "C310",
                "tipo_consolidacion": "Un registro por hora"
            },
            {
                "tag": "C310AI__14",
                "tiempo": "07/11/2025 03:00",
                "valor": 6.53,
                "value_formateado": "6.530",
                "remota": "C310",
                "tipo_consolidacion": "Un registro por hora"
            },
            {
                "tag": "C310AI__14",
                "tiempo": "07/11/2025 04:00",
                "valor": 6.46,
                "value_formateado": "6.460",
                "remota": "C310",
                "tipo_consolidacion": "Un registro por hora"
            },
            {
                "tag": "C310AI__14",
                "tiempo": "07/11/2025 05:00",
                "valor": 6.55,
                "value_formateado": "6.550",
                "remota": "C310",
                "tipo_consolidacion": "Un registro por hora"
            },
            {
                "tag": "C310AI__14",
                "tiempo": "07/11/2025 06:00",
                "valor": 6.24,
                "value_formateado": "6.240",
                "remota": "C310",
                "tipo_consolidacion": "Un registro por hora"
            },
            {
                "tag": "C310AI__14",
                "tiempo": "07/11/2025 07:00",
                "valor": 6.42,
                "value_formateado": "6.420",
                "remota": "C310",
                "tipo_consolidacion": "Un registro por hora"
            },
            {
                "tag": "C310AI__14",
                "tiempo": "07/11/2025 08:00",
                "valor": 6.57,
                "value_formateado": "6.570",
                "remota": "C310",
                "tipo_consolidacion": "Un registro por hora"
            },
            {
                "tag": "C310AI__14",
                "tiempo": "07/11/2025 09:00",
                "valor": 6.39,
                "value_formateado": "6.390",
                "remota": "C310",
                "tipo_consolidacion": "Un registro por hora"
            },
            {
                "tag": "C310AI__14",
                "tiempo": "07/11/2025 10:00",
                "valor": 6.58,
                "value_formateado": "6.580",
                "remota": "C310",
                "tipo_consolidacion": "Un registro por hora"
            },
            {
                "tag": "C310AI__14",
                "tiempo": "07/11/2025 11:00",
                "valor": 6.6,
                "value_formateado": "6.600",
                "remota": "C310",
                "tipo_consolidacion": "Un registro por hora"
            },
            {
                "tag": "C310AI__14",
                "tiempo": "07/11/2025 12:00",
                "valor": 6.82,
                "value_formateado": "6.820",
                "remota": "C310",
                "tipo_consolidacion": "Un registro por hora"
            },
            {
                "tag": "C310AI__14",
                "tiempo": "07/11/2025 13:00",
                "valor": 7.08,
                "value_formateado": "7.080",
                "remota": "C310",
                "tipo_consolidacion": "Un registro por hora"
            },
            {
                "tag": "C310AI__14",
                "tiempo": "07/11/2025 14:00",
                "valor": 7.25,
                "value_formateado": "7.250",
                "remota": "C310",
                "tipo_consolidacion": "Un registro por hora"
            },
            {
                "tag": "C310AI__14",
                "tiempo": "07/11/2025 15:00",
                "valor": 7.4,
                "value_formateado": "7.400",
                "remota": "C310",
                "tipo_consolidacion": "Un registro por hora"
            },
            {
                "tag": "C310AI__14",
                "tiempo": "07/11/2025 16:00",
                "valor": 7.27,
                "value_formateado": "7.270",
                "remota": "C310",
                "tipo_consolidacion": "Un registro por hora"
            },
            {
                "tag": "C310AI__14",
                "tiempo": "07/11/2025 17:00",
                "valor": 7.69,
                "value_formateado": "7.690",
                "remota": "C310",
                "tipo_consolidacion": "Un registro por hora"
            },
            {
                "tag": "C310AI__14",
                "tiempo": "07/11/2025 18:00",
                "valor": 7.58,
                "value_formateado": "7.580",
                "remota": "C310",
                "tipo_consolidacion": "Un registro por hora"
            },
            {
                "tag": "C310AI__14",
                "tiempo": "07/11/2025 19:00",
                "valor": 7.61,
                "value_formateado": "7.610",
                "remota": "C310",
                "tipo_consolidacion": "Un registro por hora"
            },
            {
                "tag": "C310AI__14",
                "tiempo": "07/11/2025 20:00",
                "valor": 7.43,
                "value_formateado": "7.430",
                "remota": "C310",
                "tipo_consolidacion": "Un registro por hora"
            },
            {
                "tag": "C310AI__14",
                "tiempo": "07/11/2025 21:00",
                "valor": 7.48,
                "value_formateado": "7.480",
                "remota": "C310",
                "tipo_consolidacion": "Un registro por hora"
            },
            {
                "tag": "C310AI__14",
                "tiempo": "07/11/2025 22:00",
                "valor": 7.48,
                "value_formateado": "7.480",
                "remota": "C310",
                "tipo_consolidacion": "Un registro por hora"
            },
            {
                "tag": "C310AI__14",
                "tiempo": "07/11/2025 23:00",
                "valor": 7.27,
                "value_formateado": "7.270",
                "remota": "C310",
                "tipo_consolidacion": "Un registro por hora"
            },
            {
                "tag": "C310AI__14",
                "tiempo": "08/11/2025 00:00",
                "valor": 7.5,
                "value_formateado": "7.500",
                "remota": "C310",
                "tipo_consolidacion": "Un registro por hora"
            },
            {
                "tag": "C310AI__14",
                "tiempo": "08/11/2025 01:00",
                "valor": 7.44,
                "value_formateado": "7.440",
                "remota": "C310",
                "tipo_consolidacion": "Un registro por hora"
            },
            {
                "tag": "C310AI__14",
                "tiempo": "08/11/2025 02:00",
                "valor": 7.45,
                "value_formateado": "7.450",
                "remota": "C310",
                "tipo_consolidacion": "Un registro por hora"
            },
            {
                "tag": "C310AI__14",
                "tiempo": "08/11/2025 03:00",
                "valor": 7.41,
                "value_formateado": "7.410",
                "remota": "C310",
                "tipo_consolidacion": "Un registro por hora"
            },
            {
                "tag": "C310AI__14",
                "tiempo": "08/11/2025 04:00",
                "valor": 7.44,
                "value_formateado": "7.440",
                "remota": "C310",
                "tipo_consolidacion": "Un registro por hora"
            },
            {
                "tag": "C310AI__14",
                "tiempo": "08/11/2025 05:00",
                "valor": 7.42,
                "value_formateado": "7.420",
                "remota": "C310",
                "tipo_consolidacion": "Un registro por hora"
            },
            {
                "tag": "C310AI__14",
                "tiempo": "08/11/2025 06:00",
                "valor": 7.37,
                "value_formateado": "7.370",
                "remota": "C310",
                "tipo_consolidacion": "Un registro por hora"
            },
            {
                "tag": "C310AI__14",
                "tiempo": "08/11/2025 07:00",
                "valor": 7.41,
                "value_formateado": "7.410",
                "remota": "C310",
                "tipo_consolidacion": "Un registro por hora"
            },
            {
                "tag": "C310AI__14",
                "tiempo": "08/11/2025 08:00",
                "valor": 7.37,
                "value_formateado": "7.370",
                "remota": "C310",
                "tipo_consolidacion": "Un registro por hora"
            },
            {
                "tag": "C310AI__14",
                "tiempo": "08/11/2025 09:00",
                "valor": 7.41,
                "value_formateado": "7.410",
                "remota": "C310",
                "tipo_consolidacion": "Un registro por hora"
            },
            {
                "tag": "C310AI__14",
                "tiempo": "08/11/2025 10:00",
                "valor": 7.23,
                "value_formateado": "7.230",
                "remota": "C310",
                "tipo_consolidacion": "Un registro por hora"
            },
            {
                "tag": "C310AI__14",
                "tiempo": "08/11/2025 11:00",
                "valor": 7.13,
                "value_formateado": "7.130",
                "remota": "C310",
                "tipo_consolidacion": "Un registro por hora"
            },
            {
                "tag": "C310AI__14",
                "tiempo": "08/11/2025 12:00",
                "valor": 7.44,
                "value_formateado": "7.440",
                "remota": "C310",
                "tipo_consolidacion": "Un registro por hora"
            },
            {
                "tag": "C310AI__14",
                "tiempo": "08/11/2025 13:00",
                "valor": 7.47,
                "value_formateado": "7.470",
                "remota": "C310",
                "tipo_consolidacion": "Un registro por hora"
            },
            {
                "tag": "C310AI__14",
                "tiempo": "08/11/2025 14:00",
                "valor": 7.55,
                "value_formateado": "7.550",
                "remota": "C310",
                "tipo_consolidacion": "Un registro por hora"
            },
            {
                "tag": "C310AI__14",
                "tiempo": "08/11/2025 15:00",
                "valor": 7.55,
                "value_formateado": "7.550",
                "remota": "C310",
                "tipo_consolidacion": "Un registro por hora"
            },
            {
                "tag": "C310AI__14",
                "tiempo": "08/11/2025 16:00",
                "valor": 7.72,
                "value_formateado": "7.720",
                "remota": "C310",
                "tipo_consolidacion": "Un registro por hora"
            },
            {
                "tag": "C310AI__14",
                "tiempo": "08/11/2025 17:00",
                "valor": 7.85,
                "value_formateado": "7.850",
                "remota": "C310",
                "tipo_consolidacion": "Un registro por hora"
            },
            {
                "tag": "C310AI__14",
                "tiempo": "08/11/2025 18:00",
                "valor": 7.75,
                "value_formateado": "7.750",
                "remota": "C310",
                "tipo_consolidacion": "Un registro por hora"
            },
            {
                "tag": "C310AI__14",
                "tiempo": "08/11/2025 19:00",
                "valor": 7.77,
                "value_formateado": "7.770",
                "remota": "C310",
                "tipo_consolidacion": "Un registro por hora"
            },
            {
                "tag": "C310AI__14",
                "tiempo": "08/11/2025 20:00",
                "valor": 7.45,
                "value_formateado": "7.450",
                "remota": "C310",
                "tipo_consolidacion": "Un registro por hora"
            },
            {
                "tag": "C310AI__14",
                "tiempo": "08/11/2025 21:00",
                "valor": 7.57,
                "value_formateado": "7.570",
                "remota": "C310",
                "tipo_consolidacion": "Un registro por hora"
            },
            {
                "tag": "C310AI__14",
                "tiempo": "08/11/2025 22:00",
                "valor": 7.42,
                "value_formateado": "7.420",
                "remota": "C310",
                "tipo_consolidacion": "Un registro por hora"
            },
            {
                "tag": "C310AI__14",
                "tiempo": "08/11/2025 23:00",
                "valor": 7.56,
                "value_formateado": "7.560",
                "remota": "C310",
                "tipo_consolidacion": "Un registro por hora"
            },
            {
                "tag": "C310AI__14",
                "tiempo": "09/11/2025 00:00",
                "valor": 7.42,
                "value_formateado": "7.420",
                "remota": "C310",
                "tipo_consolidacion": "Un registro por hora"
            },
            {
                "tag": "C310AI__14",
                "tiempo": "09/11/2025 01:00",
                "valor": 7.42,
                "value_formateado": "7.420",
                "remota": "C310",
                "tipo_consolidacion": "Un registro por hora"
            },
            {
                "tag": "C310AI__14",
                "tiempo": "09/11/2025 02:00",
                "valor": 7.36,
                "value_formateado": "7.360",
                "remota": "C310",
                "tipo_consolidacion": "Un registro por hora"
            },
            {
                "tag": "C310AI__14",
                "tiempo": "09/11/2025 03:00",
                "valor": 7.29,
                "value_formateado": "7.290",
                "remota": "C310",
                "tipo_consolidacion": "Un registro por hora"
            },
            {
                "tag": "C310AI__14",
                "tiempo": "09/11/2025 04:00",
                "valor": 7.3,
                "value_formateado": "7.300",
                "remota": "C310",
                "tipo_consolidacion": "Un registro por hora"
            },
            {
                "tag": "C310AI__14",
                "tiempo": "09/11/2025 05:00",
                "valor": 7.35,
                "value_formateado": "7.350",
                "remota": "C310",
                "tipo_consolidacion": "Un registro por hora"
            },
            {
                "tag": "C310AI__14",
                "tiempo": "09/11/2025 06:00",
                "valor": 7.19,
                "value_formateado": "7.190",
                "remota": "C310",
                "tipo_consolidacion": "Un registro por hora"
            },
            {
                "tag": "C310AI__14",
                "tiempo": "09/11/2025 07:00",
                "valor": 7.28,
                "value_formateado": "7.280",
                "remota": "C310",
                "tipo_consolidacion": "Un registro por hora"
            },
            {
                "tag": "C310AI__14",
                "tiempo": "09/11/2025 08:00",
                "valor": 7.25,
                "value_formateado": "7.250",
                "remota": "C310",
                "tipo_consolidacion": "Un registro por hora"
            },
            {
                "tag": "C310AI__14",
                "tiempo": "09/11/2025 09:00",
                "valor": 7.44,
                "value_formateado": "7.440",
                "remota": "C310",
                "tipo_consolidacion": "Un registro por hora"
            },
            {
                "tag": "C310AI__14",
                "tiempo": "09/11/2025 10:00",
                "valor": 7.5,
                "value_formateado": "7.500",
                "remota": "C310",
                "tipo_consolidacion": "Un registro por hora"
            },
            {
                "tag": "C310AI__14",
                "tiempo": "09/11/2025 11:00",
                "valor": 7.7,
                "value_formateado": "7.700",
                "remota": "C310",
                "tipo_consolidacion": "Un registro por hora"
            },
            {
                "tag": "C310AI__14",
                "tiempo": "09/11/2025 12:00",
                "valor": 7.75,
                "value_formateado": "7.750",
                "remota": "C310",
                "tipo_consolidacion": "Un registro por hora"
            },
            {
                "tag": "C310AI__14",
                "tiempo": "09/11/2025 13:00",
                "valor": 7.71,
                "value_formateado": "7.710",
                "remota": "C310",
                "tipo_consolidacion": "Un registro por hora"
            },
            {
                "tag": "C310AI__14",
                "tiempo": "09/11/2025 14:00",
                "valor": 7.65,
                "value_formateado": "7.650",
                "remota": "C310",
                "tipo_consolidacion": "Un registro por hora"
            },
            {
                "tag": "C310AI__14",
                "tiempo": "09/11/2025 15:00",
                "valor": 7.71,
                "value_formateado": "7.710",
                "remota": "C310",
                "tipo_consolidacion": "Un registro por hora"
            },
            {
                "tag": "C310AI__14",
                "tiempo": "09/11/2025 16:00",
                "valor": 7.92,
                "value_formateado": "7.920",
                "remota": "C310",
                "tipo_consolidacion": "Un registro por hora"
            },
            {
                "tag": "C310AI__14",
                "tiempo": "09/11/2025 17:00",
                "valor": 7.95,
                "value_formateado": "7.950",
                "remota": "C310",
                "tipo_consolidacion": "Un registro por hora"
            },
            {
                "tag": "C310AI__14",
                "tiempo": "09/11/2025 18:00",
                "valor": 7.89,
                "value_formateado": "7.890",
                "remota": "C310",
                "tipo_consolidacion": "Un registro por hora"
            }
        ],
        "ok": 1
    }
}